django_logikal/__init__.py
django_logikal/apps.py
django_logikal/bibliography.py
django_logikal/email.py
django_logikal/env.py
django_logikal/local_data.py
django_logikal/logging.py
django_logikal/manage.py
django_logikal/middleware.py
django_logikal/models.py
django_logikal/py.typed
django_logikal/run.py
django_logikal/security.py
django_logikal/sitemap.py
django_logikal/static.py
django_logikal/urls.py
django_logikal/validation.py
django_logikal/views.py
django_logikal/babel/django.ini
django_logikal/babel/djangojs.ini
django_logikal/management/__init__.py
django_logikal/management/commands/__init__.py
django_logikal/management/commands/generate.py
django_logikal/management/commands/syncdb.py
django_logikal/management/commands/translate.py
django_logikal/migration/__init__.py
django_logikal/migration/writer.py
django_logikal/migration/operations/__init__.py
django_logikal/migration/operations/model.py
django_logikal/migration/operations/schema.py
django_logikal/migration/operations/table.py
django_logikal/migration/operations/user.py
django_logikal/settings/__init__.py
django_logikal/settings/common/__init__.py
django_logikal/settings/common/base.py
django_logikal/settings/common/dev.py
django_logikal/settings/common/production.py
django_logikal/settings/common/testing.py
django_logikal/settings/dynamic_site/__init__.py
django_logikal/settings/dynamic_site/base.py
django_logikal/settings/dynamic_site/dev.py
django_logikal/settings/dynamic_site/production.py
django_logikal/settings/dynamic_site/testing.py
django_logikal/settings/static_site/__init__.py
django_logikal/settings/static_site/base.py
django_logikal/settings/static_site/dev.py
django_logikal/settings/static_site/testing.py
django_logikal/static/django_logikal/fonts.css
django_logikal/static/django_logikal/validation_error.css
django_logikal/static/django_logikal/fonts/Lato-Bold.ttf
django_logikal/static/django_logikal/fonts/Lato-Bold.woff
django_logikal/static/django_logikal/fonts/Lato-Bold.woff2
django_logikal-3.17.1.dist-info/licenses/LICENSE.txt
django_logikal-3.17.1.dist-info/METADATA
django_logikal-3.17.1.dist-info/WHEEL
django_logikal-3.17.1.dist-info/entry_points.txt
django_logikal-3.17.1.dist-info/top_level.txt
django_logikal-3.17.1.dist-info/RECORD
