Metadata-Version: 2.4
Name: django-logikal
Version: 3.17.1
Summary: Django utilities used at Logikal
Author-email: Logikal GmbH <contact@logikal.io>
License-Expression: MIT
Project-URL: Documentation, https://docs.logikal.io/django-logikal/
Project-URL: Release notes, https://github.com/logikal-io/django-logikal/releases
Project-URL: Issue tracker, https://github.com/logikal-io/django-logikal/issues
Project-URL: Source code, https://github.com/logikal-io/django-logikal
Keywords: python,django
Classifier: Development Status :: 5 - Production/Stable
Classifier: Intended Audience :: Developers
Classifier: Operating System :: POSIX :: Linux
Classifier: Programming Language :: Python :: 3
Classifier: Programming Language :: Python :: 3.12
Classifier: Framework :: Django
Classifier: Framework :: Django :: 5
Classifier: Topic :: Software Development
Classifier: Topic :: Utilities
Classifier: Typing :: Typed
Requires-Python: ~=3.12
License-File: LICENSE.txt
Requires-Dist: Django~=5.2
Requires-Dist: django-stubs-ext~=5.2
Requires-Dist: django-debug-toolbar~=5.2
Requires-Dist: django-debug-toolbar-template-profiler~=2.1
Requires-Dist: django-mail-panel~=4.1
Requires-Dist: django-csp~=4.0
Requires-Dist: django-robots~=6.1
Requires-Dist: django-simple-history~=3.10
Requires-Dist: psycopg~=3.2
Requires-Dist: factory-boy~=3.3
Requires-Dist: babel~=2.17
Requires-Dist: black~=25.11
Requires-Dist: termcolor~=3.2
Requires-Dist: google-cloud-logging~=3.12
Requires-Dist: Jinja2~=3.1
Requires-Dist: logikal-utils[docker]~=1.4
Requires-Dist: Pygments~=2.19
Provides-Extra: static
Requires-Dist: django-distill~=3.2; extra == "static"
Provides-Extra: dynamic
Requires-Dist: whitenoise[brotli]~=6.11; extra == "dynamic"
Requires-Dist: stormware[amazon,google]~=2.2; extra == "dynamic"
Requires-Dist: antimarkdown~=1.0; extra == "dynamic"
Requires-Dist: django-anymail[amazon-ses]~=13.1; extra == "dynamic"
Requires-Dist: premailer~=3.10; extra == "dynamic"
Provides-Extra: rest
Requires-Dist: djangorestframework~=3.16; extra == "rest"
Requires-Dist: djangorestframework-stubs; extra == "rest"
Provides-Extra: bibliography
Requires-Dist: pybtex==0.25.1; extra == "bibliography"
Dynamic: license-file
